[
{"name": "Bitcoin", "acronym": "BTC", "price": 96089.8, "price_currency_exchange": ["USD"], "variance_percent": "−0.64%", "market_cap": "1.9 T", "market_cap_currency_exchange": "USD", "volume": "54.21 B", "volume_currency_exchange": "USD", "circulating_supply": "19.82 M"},
{"name": "Ethereum", "acronym": "ETH", "price": 2622.89, "price_currency_exchange": ["USD"], "variance_percent": "−3.23%", "market_cap": "316.14 B", "market_cap_currency_exchange": "USD", "volume": "27.54 B", "volume_currency_exchange": "USD", "circulating_supply": "120.53 M"},
{"name": "Tether USDt", "acronym": "USDT", "price": 1.0002, "price_currency_exchange": ["USD"], "variance_percent": "+0.01%", "market_cap": "141.38 B", "market_cap_currency_exchange": "USD", "volume": "104.81 B", "volume_currency_exchange": "USD", "circulating_supply": "141.36 B"},
{"name": "XRP", "acronym": "XRP", "price": 2.3868, "price_currency_exchange": ["USD"], "variance_percent": "+2.04%", "market_cap": "137.87 B", "market_cap_currency_exchange": "USD", "volume": "8.94 B", "volume_currency_exchange": "USD", "circulating_supply": "57.76 B"},
{"name": "Solana", "acronym": "SOL", "price": 191.78, "price_currency_exchange": ["USD"], "variance_percent": "−0.19%", "market_cap": "93.53 B", "market_cap_currency_exchange": "USD", "volume": "4.6 B", "volume_currency_exchange": "USD", "circulating_supply": "487.72 M"},
{"name": "BNB", "acronym": "BNB", "price": 576.61, "price_currency_exchange": ["USD"], "variance_percent": "−0.62%", "market_cap": "82.16 B", "market_cap_currency_exchange": "USD", "volume": "1.57 B", "volume_currency_exchange": "USD", "circulating_supply": "142.48 M"},
{"name": "USDC", "acronym": "USDC", "price": 0.99986, "price_currency_exchange": ["USD"], "variance_percent": "−0.01%", "market_cap": "56.2 B", "market_cap_currency_exchange": "USD", "volume": "9.22 B", "volume_currency_exchange": "USD", "circulating_supply": "56.21 B"},
{"name": "Dogecoin", "acronym": "DOGE", "price": 0.2477, "price_currency_exchange": ["USD"], "variance_percent": "−0.35%", "market_cap": "36.65 B", "market_cap_currency_exchange": "USD", "volume": "1.98 B", "volume_currency_exchange": "USD", "circulating_supply": "147.95 B"},
{"name": "Cardano", "acronym": "ADA", "price": 0.70471, "price_currency_exchange": ["USD"], "variance_percent": "−1.41%", "market_cap": "24.8 B", "market_cap_currency_exchange": "USD", "volume": "896.74 M", "volume_currency_exchange": "USD", "circulating_supply": "35.19 B"},
{"name": "TRON", "acronym": "TRX", "price": 0.23117, "price_currency_exchange": ["USD"], "variance_percent": "+0.39%", "market_cap": "19.91 B", "market_cap_currency_exchange": "USD", "volume": "692.31 M", "volume_currency_exchange": "USD", "circulating_supply": "86.11 B"},
{"name": "Chainlink", "acronym": "LINK", "price": 18.389, "price_currency_exchange": ["USD"], "variance_percent": "−2.01%", "market_cap": "11.73 B", "market_cap_currency_exchange": "USD", "volume": "574.96 M", "volume_currency_exchange": "USD", "circulating_supply": "638.1 M"},
{"name": "Avalanche", "acronym": "AVAX", "price": 24.299, "price_currency_exchange": ["USD"], "variance_percent": "−2.35%", "market_cap": "10.01 B", "market_cap_currency_exchange": "USD", "volume": "359.13 M", "volume_currency_exchange": "USD", "circulating_supply": "411.8 M"},
{"name": "Stellar", "acronym": "XLM", "price": 0.3288, "price_currency_exchange": ["USD"], "variance_percent": "+2.34%", "market_cap": "10.06 B", "market_cap_currency_exchange": "USD", "volume": "373.89 M", "volume_currency_exchange": "USD", "circulating_supply": "30.59 B"},
{"name": "Sui", "acronym": "SUI", "price": 2.9963, "price_currency_exchange": ["USD"], "variance_percent": "−5.58%", "market_cap": "9.26 B", "market_cap_currency_exchange": "USD", "volume": "1.31 B", "volume_currency_exchange": "USD", "circulating_supply": "3.09 B"},
{"name": "Toncoin", "acronym": "TON", "price": 3.7297, "price_currency_exchange": ["USD"], "variance_percent": "−0.93%", "market_cap": "9.3 B", "market_cap_currency_exchange": "USD", "volume": "158.79 M", "volume_currency_exchange": "USD", "circulating_supply": "2.49 B"},
{"name": "UNUS SED LEO", "acronym": "LEO", "price": 9.8274, "price_currency_exchange": ["USD"], "variance_percent": "+0.05%", "market_cap": "9.08 B", "market_cap_currency_exchange": "USD", "volume": "670.27 K", "volume_currency_exchange": "USD", "circulating_supply": "924.16 M"},
{"name": "Hedera", "acronym": "HBAR", "price": 0.23353, "price_currency_exchange": ["USD"], "variance_percent": "+0.88%", "market_cap": "8.94 B", "market_cap_currency_exchange": "USD", "volume": "346.59 M", "volume_currency_exchange": "USD", "circulating_supply": "38.27 B"},
{"name": "Shiba Inu", "acronym": "SHIB", "price": 1.5101e-05, "price_currency_exchange": ["USD"], "variance_percent": "+0.19%", "market_cap": "8.9 B", "market_cap_currency_exchange": "USD", "volume": "339.7 M", "volume_currency_exchange": "USD", "circulating_supply": "589.25 T"},
{"name": "Bitget Token", "acronym": "BGB", "price": 6.6147, "price_currency_exchange": ["USD"], "variance_percent": "−2.04%", "market_cap": "7.94 B", "market_cap_currency_exchange": "USD", "volume": "411.36 M", "volume_currency_exchange": "USD", "circulating_supply": "1.2 B"},
{"name": "Hyperliquid", "acronym": "HYPE", "price": 22.968, "price_currency_exchange": ["USD"], "variance_percent": "−5.75%", "market_cap": "7.67 B", "market_cap_currency_exchange": "USD", "volume": "199.01 M", "volume_currency_exchange": "USD", "circulating_supply": "333.93 M"},
{"name": "Litecoin", "acronym": "LTC", "price": 101.83, "price_currency_exchange": ["USD"], "variance_percent": "+0.36%", "market_cap": "7.69 B", "market_cap_currency_exchange": "USD", "volume": "777.66 M", "volume_currency_exchange": "USD", "circulating_supply": "75.51 M"},
{"name": "Polkadot", "acronym": "DOT", "price": 4.6063, "price_currency_exchange": ["USD"], "variance_percent": "+1.12%", "market_cap": "7.12 B", "market_cap_currency_exchange": "USD", "volume": "283.57 M", "volume_currency_exchange": "USD", "circulating_supply": "1.55 B"},
{"name": "Bitcoin Cash", "acronym": "BCH", "price": 319.27, "price_currency_exchange": ["USD"], "variance_percent": "+0.05%", "market_cap": "6.33 B", "market_cap_currency_exchange": "USD", "volume": "261.78 M", "volume_currency_exchange": "USD", "circulating_supply": "19.83 M"},
{"name": "Ethena USDe", "acronym": "USDE", "price": 1.0001, "price_currency_exchange": ["USD"], "variance_percent": "−0.01%", "market_cap": "6.05 B", "market_cap_currency_exchange": "USD", "volume": "62.74 M", "volume_currency_exchange": "USD", "circulating_supply": "6.05 B"},
{"name": "MANTRA", "acronym": "OM", "price": 6.062, "price_currency_exchange": ["USD"], "variance_percent": "+2.32%", "market_cap": "5.89 B", "market_cap_currency_exchange": "USD", "volume": "349.3 M", "volume_currency_exchange": "USD", "circulating_supply": "971.37 M"},
{"name": "Uniswap", "acronym": "UNI", "price": 9.0377, "price_currency_exchange": ["USD"], "variance_percent": "+0.00%", "market_cap": "5.43 B", "market_cap_currency_exchange": "USD", "volume": "252.03 M", "volume_currency_exchange": "USD", "circulating_supply": "600.52 M"},
{"name": "Dai", "acronym": "DAI", "price": 0.99968, "price_currency_exchange": ["USD"], "variance_percent": "−0.01%", "market_cap": "5.36 B", "market_cap_currency_exchange": "USD", "volume": "221.47 M", "volume_currency_exchange": "USD", "circulating_supply": "5.37 B"},
{"name": "Ondo", "acronym": "ONDO", "price": 1.3728, "price_currency_exchange": ["USD"], "variance_percent": "+0.93%", "market_cap": "4.34 B", "market_cap_currency_exchange": "USD", "volume": "682.55 M", "volume_currency_exchange": "USD", "circulating_supply": "3.16 B"},
{"name": "Pepe", "acronym": "PEPE", "price": 9.0836e-06, "price_currency_exchange": ["USD"], "variance_percent": "−3.22%", "market_cap": "3.82 B", "market_cap_currency_exchange": "USD", "volume": "847.22 M", "volume_currency_exchange": "USD", "circulating_supply": "420.69 T"},
{"name": "NEAR Protocol", "acronym": "NEAR", "price": 3.2188, "price_currency_exchange": ["USD"], "variance_percent": "+1.02%", "market_cap": "3.79 B", "market_cap_currency_exchange": "USD", "volume": "179.42 M", "volume_currency_exchange": "USD", "circulating_supply": "1.18 B"},
{"name": "Monero", "acronym": "XMR", "price": 196.37, "price_currency_exchange": ["USD"], "variance_percent": "−12.76%", "market_cap": "3.62 B", "market_cap_currency_exchange": "USD", "volume": "60.1 M", "volume_currency_exchange": "USD", "circulating_supply": "18.45 M"},
{"name": "Aave", "acronym": "AAVE", "price": 238.53, "price_currency_exchange": ["USD"], "variance_percent": "−2.82%", "market_cap": "3.59 B", "market_cap_currency_exchange": "USD", "volume": "372.23 M", "volume_currency_exchange": "USD", "circulating_supply": "15.06 M"},
{"name": "Mantle", "acronym": "MNT", "price": 1.0526, "price_currency_exchange": ["USD"], "variance_percent": "−4.48%", "market_cap": "3.54 B", "market_cap_currency_exchange": "USD", "volume": "166.37 M", "volume_currency_exchange": "USD", "circulating_supply": "3.36 B"},
{"name": "OFFICIAL TRUMP", "acronym": "TRUMP", "price": 16.765, "price_currency_exchange": ["USD"], "variance_percent": "−3.30%", "market_cap": "3.35 B", "market_cap_currency_exchange": "USD", "volume": "1.49 B", "volume_currency_exchange": "USD", "circulating_supply": "200 M"},
{"name": "Internet Computer", "acronym": "ICP", "price": 6.809, "price_currency_exchange": ["USD"], "variance_percent": "+0.39%", "market_cap": "3.27 B", "market_cap_currency_exchange": "USD", "volume": "85.95 M", "volume_currency_exchange": "USD", "circulating_supply": "480.46 M"},
{"name": "Aptos", "acronym": "APT", "price": 5.7081, "price_currency_exchange": ["USD"], "variance_percent": "−1.43%", "market_cap": "3.28 B", "market_cap_currency_exchange": "USD", "volume": "309.49 M", "volume_currency_exchange": "USD", "circulating_supply": "574.33 M"},
{"name": "Ethereum Classic", "acronym": "ETC", "price": 19.77, "price_currency_exchange": ["USD"], "variance_percent": "−0.77%", "market_cap": "2.98 B", "market_cap_currency_exchange": "USD", "volume": "165.22 M", "volume_currency_exchange": "USD", "circulating_supply": "150.66 M"},
{"name": "OKB", "acronym": "OKB", "price": 46.384, "price_currency_exchange": ["USD"], "variance_percent": "+0.47%", "market_cap": "2.78 B", "market_cap_currency_exchange": "USD", "volume": "5.09 M", "volume_currency_exchange": "USD", "circulating_supply": "60 M"},
{"name": "VeChain", "acronym": "VET", "price": 0.032694, "price_currency_exchange": ["USD"], "variance_percent": "−0.35%", "market_cap": "2.65 B", "market_cap_currency_exchange": "USD", "volume": "65.75 M", "volume_currency_exchange": "USD", "circulating_supply": "80.99 B"},
{"name": "Bittensor", "acronym": "TAO", "price": 315.81, "price_currency_exchange": ["USD"], "variance_percent": "−5.83%", "market_cap": "2.59 B", "market_cap_currency_exchange": "USD", "volume": "183.83 M", "volume_currency_exchange": "USD", "circulating_supply": "8.22 M"},
{"name": "POL (ex-MATIC)", "acronym": "POL", "price": 0.29827, "price_currency_exchange": ["USD"], "variance_percent": "−0.67%", "market_cap": "2.55 B", "market_cap_currency_exchange": "USD", "volume": "139.57 M", "volume_currency_exchange": "USD", "circulating_supply": "8.55 B"},
{"name": "Cronos", "acronym": "CRO", "price": 0.093589, "price_currency_exchange": ["USD"], "variance_percent": "−2.72%", "market_cap": "2.49 B", "market_cap_currency_exchange": "USD", "volume": "22.8 M", "volume_currency_exchange": "USD", "circulating_supply": "26.57 B"},
{"name": "Algorand", "acronym": "ALGO", "price": 0.27124, "price_currency_exchange": ["USD"], "variance_percent": "+0.08%", "market_cap": "2.29 B", "market_cap_currency_exchange": "USD", "volume": "167.23 M", "volume_currency_exchange": "USD", "circulating_supply": "8.42 B"},
{"name": "Kaspa", "acronym": "KAS", "price": 0.085244, "price_currency_exchange": ["USD"], "variance_percent": "−0.65%", "market_cap": "2.19 B", "market_cap_currency_exchange": "USD", "volume": "103 M", "volume_currency_exchange": "USD", "circulating_supply": "25.69 B"},
{"name": "Render", "acronym": "RENDER", "price": 4.1337, "price_currency_exchange": ["USD"], "variance_percent": "−3.68%", "market_cap": "2.14 B", "market_cap_currency_exchange": "USD", "volume": "90.85 M", "volume_currency_exchange": "USD", "circulating_supply": "517.72 M"},
{"name": "Jupiter", "acronym": "JUP", "price": 0.79484, "price_currency_exchange": ["USD"], "variance_percent": "−5.69%", "market_cap": "2.1 B", "market_cap_currency_exchange": "USD", "volume": "176.11 M", "volume_currency_exchange": "USD", "circulating_supply": "2.64 B"},
{"name": "Filecoin", "acronym": "FIL", "price": 3.1783, "price_currency_exchange": ["USD"], "variance_percent": "+0.75%", "market_cap": "2 B", "market_cap_currency_exchange": "USD", "volume": "174.71 M", "volume_currency_exchange": "USD", "circulating_supply": "628.19 M"},
{"name": "Arbitrum", "acronym": "ARB", "price": 0.42942, "price_currency_exchange": ["USD"], "variance_percent": "−4.76%", "market_cap": "1.87 B", "market_cap_currency_exchange": "USD", "volume": "260.74 M", "volume_currency_exchange": "USD", "circulating_supply": "4.34 B"},
{"name": "GateToken", "acronym": "GT", "price": 20.645, "price_currency_exchange": ["USD"], "variance_percent": "+1.23%", "market_cap": "1.83 B", "market_cap_currency_exchange": "USD", "volume": "14.81 M", "volume_currency_exchange": "USD", "circulating_supply": "88.75 M"},
{"name": "First Digital USD", "acronym": "FDUSD", "price": 0.99893, "price_currency_exchange": ["USD"], "variance_percent": "−0.03%", "market_cap": "1.82 B", "market_cap_currency_exchange": "USD", "volume": "6.65 B", "volume_currency_exchange": "USD", "circulating_supply": "1.82 B"},
{"name": "Artificial Superintelligence Alliance", "acronym": "FET", "price": 0.73142, "price_currency_exchange": ["USD"], "variance_percent": "+1.12%", "market_cap": "1.75 B", "market_cap_currency_exchange": "USD", "volume": "152.46 M", "volume_currency_exchange": "USD", "circulating_supply": "2.39 B"},
{"name": "Cosmos", "acronym": "ATOM", "price": 4.3735, "price_currency_exchange": ["USD"], "variance_percent": "−1.64%", "market_cap": "1.71 B", "market_cap_currency_exchange": "USD", "volume": "189.47 M", "volume_currency_exchange": "USD", "circulating_supply": "390.93 M"},
{"name": "DeXe", "acronym": "DEXE", "price": 20.359, "price_currency_exchange": ["USD"], "variance_percent": "−0.50%", "market_cap": "1.7 B", "market_cap_currency_exchange": "USD", "volume": "13.81 M", "volume_currency_exchange": "USD", "circulating_supply": "83.73 M"},
{"name": "Ethena", "acronym": "ENA", "price": 0.49937, "price_currency_exchange": ["USD"], "variance_percent": "+1.82%", "market_cap": "1.56 B", "market_cap_currency_exchange": "USD", "volume": "413.34 M", "volume_currency_exchange": "USD", "circulating_supply": "3.13 B"},
{"name": "KuCoin Token", "acronym": "KCS", "price": 12.325, "price_currency_exchange": ["USD"], "variance_percent": "−1.26%", "market_cap": "1.51 B", "market_cap_currency_exchange": "USD", "volume": "1.5 M", "volume_currency_exchange": "USD", "circulating_supply": "122.61 M"},
{"name": "Celestia", "acronym": "TIA", "price": 2.8163, "price_currency_exchange": ["USD"], "variance_percent": "−4.29%", "market_cap": "1.46 B", "market_cap_currency_exchange": "USD", "volume": "82 M", "volume_currency_exchange": "USD", "circulating_supply": "519.12 M"},
{"name": "Raydium", "acronym": "RAY", "price": 4.9937, "price_currency_exchange": ["USD"], "variance_percent": "−4.03%", "market_cap": "1.45 B", "market_cap_currency_exchange": "USD", "volume": "138.68 M", "volume_currency_exchange": "USD", "circulating_supply": "290.87 M"},
{"name": "Lido DAO", "acronym": "LDO", "price": 1.5825, "price_currency_exchange": ["USD"], "variance_percent": "−8.55%", "market_cap": "1.42 B", "market_cap_currency_exchange": "USD", "volume": "228.42 M", "volume_currency_exchange": "USD", "circulating_supply": "895.94 M"},
{"name": "Optimism", "acronym": "OP", "price": 1.0269, "price_currency_exchange": ["USD"], "variance_percent": "−2.52%", "market_cap": "1.39 B", "market_cap_currency_exchange": "USD", "volume": "180.2 M", "volume_currency_exchange": "USD", "circulating_supply": "1.35 B"},
{"name": "XDC Network", "acronym": "XDC", "price": 0.091246, "price_currency_exchange": ["USD"], "variance_percent": "+4.06%", "market_cap": "1.36 B", "market_cap_currency_exchange": "USD", "volume": "45.92 M", "volume_currency_exchange": "USD", "circulating_supply": "14.93 B"},
{"name": "Injective", "acronym": "INJ", "price": 13.528, "price_currency_exchange": ["USD"], "variance_percent": "+1.95%", "market_cap": "1.34 B", "market_cap_currency_exchange": "USD", "volume": "136.36 M", "volume_currency_exchange": "USD", "circulating_supply": "98.97 M"},
{"name": "Immutable", "acronym": "IMX", "price": 0.76765, "price_currency_exchange": ["USD"], "variance_percent": "−0.29%", "market_cap": "1.34 B", "market_cap_currency_exchange": "USD", "volume": "43.12 M", "volume_currency_exchange": "USD", "circulating_supply": "1.74 B"},
{"name": "FLARE", "acronym": "FLR", "price": 0.022776, "price_currency_exchange": ["USD"], "variance_percent": "+17.88%", "market_cap": "1.34 B", "market_cap_currency_exchange": "USD", "volume": "35.22 M", "volume_currency_exchange": "USD", "circulating_supply": "58.76 B"},
{"name": "Theta Network", "acronym": "THETA", "price": 1.3227, "price_currency_exchange": ["USD"], "variance_percent": "+0.23%", "market_cap": "1.32 B", "market_cap_currency_exchange": "USD", "volume": "25.87 M", "volume_currency_exchange": "USD", "circulating_supply": "1 B"},
{"name": "Stacks", "acronym": "STX", "price": 0.87133, "price_currency_exchange": ["USD"], "variance_percent": "−3.25%", "market_cap": "1.32 B", "market_cap_currency_exchange": "USD", "volume": "60.66 M", "volume_currency_exchange": "USD", "circulating_supply": "1.51 B"},
{"name": "Movement", "acronym": "MOVE", "price": 0.55843, "price_currency_exchange": ["USD"], "variance_percent": "−4.67%", "market_cap": "1.31 B", "market_cap_currency_exchange": "USD", "volume": "206.59 M", "volume_currency_exchange": "USD", "circulating_supply": "2.35 B"},
{"name": "Bonk", "acronym": "BONK", "price": 1.6842e-05, "price_currency_exchange": ["USD"], "variance_percent": "−0.73%", "market_cap": "1.3 B", "market_cap_currency_exchange": "USD", "volume": "136.93 M", "volume_currency_exchange": "USD", "circulating_supply": "77.16 T"},
{"name": "The Graph", "acronym": "GRT", "price": 0.12812, "price_currency_exchange": ["USD"], "variance_percent": "−1.82%", "market_cap": "1.22 B", "market_cap_currency_exchange": "USD", "volume": "65.02 M", "volume_currency_exchange": "USD", "circulating_supply": "9.55 B"},
{"name": "Worldcoin", "acronym": "WLD", "price": 1.2034, "price_currency_exchange": ["USD"], "variance_percent": "−1.46%", "market_cap": "1.2 B", "market_cap_currency_exchange": "USD", "volume": "222.66 M", "volume_currency_exchange": "USD", "circulating_supply": "996.57 M"},
{"name": "Sonic (prev. FTM)", "acronym": "S", "price": 0.40857, "price_currency_exchange": ["USD"], "variance_percent": "−5.01%", "market_cap": "1.18 B", "market_cap_currency_exchange": "USD", "volume": "84.39 M", "volume_currency_exchange": "USD", "circulating_supply": "2.88 B"},
{"name": "JasmyCoin", "acronym": "JASMY", "price": 0.021892, "price_currency_exchange": ["USD"], "variance_percent": "+0.81%", "market_cap": "1.08 B", "market_cap_currency_exchange": "USD", "volume": "90.62 M", "volume_currency_exchange": "USD", "circulating_supply": "49.44 B"},
{"name": "Quant", "acronym": "QNT", "price": 87.472, "price_currency_exchange": ["USD"], "variance_percent": "+2.82%", "market_cap": "1.06 B", "market_cap_currency_exchange": "USD", "volume": "32.67 M", "volume_currency_exchange": "USD", "circulating_supply": "12.07 M"},
{"name": "Sei", "acronym": "SEI", "price": 0.21771, "price_currency_exchange": ["USD"], "variance_percent": "−1.74%", "market_cap": "965.03 M", "market_cap_currency_exchange": "USD", "volume": "92.23 M", "volume_currency_exchange": "USD", "circulating_supply": "4.43 B"},
{"name": "The Sandbox", "acronym": "SAND", "price": 0.37417, "price_currency_exchange": ["USD"], "variance_percent": "+0.08%", "market_cap": "915.17 M", "market_cap_currency_exchange": "USD", "volume": "117.99 M", "volume_currency_exchange": "USD", "circulating_supply": "2.45 B"},
{"name": "EOS", "acronym": "EOS", "price": 0.5844, "price_currency_exchange": ["USD"], "variance_percent": "+0.65%", "market_cap": "902.97 M", "market_cap_currency_exchange": "USD", "volume": "125.06 M", "volume_currency_exchange": "USD", "circulating_supply": "1.55 B"},
{"name": "Ethereum Name Service", "acronym": "ENS", "price": 25.055, "price_currency_exchange": ["USD"], "variance_percent": "−3.26%", "market_cap": "889.39 M", "market_cap_currency_exchange": "USD", "volume": "111.35 M", "volume_currency_exchange": "USD", "circulating_supply": "35.5 M"},
{"name": "Tezos", "acronym": "XTZ", "price": 0.83508, "price_currency_exchange": ["USD"], "variance_percent": "−0.35%", "market_cap": "859.32 M", "market_cap_currency_exchange": "USD", "volume": "40.89 M", "volume_currency_exchange": "USD", "circulating_supply": "1.03 B"},
{"name": "Nexo", "acronym": "NEXO", "price": 1.3168, "price_currency_exchange": ["USD"], "variance_percent": "−1.60%", "market_cap": "850.84 M", "market_cap_currency_exchange": "USD", "volume": "10.92 M", "volume_currency_exchange": "USD", "circulating_supply": "646.15 M"},
{"name": "BitTorrent-New", "acronym": "BTT", "price": 8.5839e-07, "price_currency_exchange": ["USD"], "variance_percent": "+0.06%", "market_cap": "846.43 M", "market_cap_currency_exchange": "USD", "volume": "24.27 M", "volume_currency_exchange": "USD", "circulating_supply": "986.06 T"},
{"name": "FLOKI", "acronym": "FLOKI", "price": 8.8044e-05, "price_currency_exchange": ["USD"], "variance_percent": "−0.66%", "market_cap": "846.18 M", "market_cap_currency_exchange": "USD", "volume": "159 M", "volume_currency_exchange": "USD", "circulating_supply": "9.61 T"},
{"name": "Onyxcoin", "acronym": "XCN", "price": 0.027463, "price_currency_exchange": ["USD"], "variance_percent": "−2.90%", "market_cap": "845.59 M", "market_cap_currency_exchange": "USD", "volume": "180.18 M", "volume_currency_exchange": "USD", "circulating_supply": "30.79 B"},
{"name": "IOTA", "acronym": "IOTA", "price": 0.21967, "price_currency_exchange": ["USD"], "variance_percent": "+3.77%", "market_cap": "797.71 M", "market_cap_currency_exchange": "USD", "volume": "51 M", "volume_currency_exchange": "USD", "circulating_supply": "3.63 B"},
{"name": "Maker", "acronym": "MKR", "price": 913.14, "price_currency_exchange": ["USD"], "variance_percent": "+1.26%", "market_cap": "803.96 M", "market_cap_currency_exchange": "USD", "volume": "88.09 M", "volume_currency_exchange": "USD", "circulating_supply": "880.43 K"},
{"name": "Gala", "acronym": "GALA", "price": 0.021387, "price_currency_exchange": ["USD"], "variance_percent": "+1.33%", "market_cap": "789.44 M", "market_cap_currency_exchange": "USD", "volume": "126.43 M", "volume_currency_exchange": "USD", "circulating_supply": "36.91 B"},
{"name": "Bitcoin SV", "acronym": "BSV", "price": 38.994, "price_currency_exchange": ["USD"], "variance_percent": "+0.20%", "market_cap": "772.94 M", "market_cap_currency_exchange": "USD", "volume": "51.3 M", "volume_currency_exchange": "USD", "circulating_supply": "19.82 M"},
{"name": "Kaia", "acronym": "KAIA", "price": 0.12941, "price_currency_exchange": ["USD"], "variance_percent": "−2.04%", "market_cap": "768.57 M", "market_cap_currency_exchange": "USD", "volume": "27.48 M", "volume_currency_exchange": "USD", "circulating_supply": "5.94 B"},
{"name": "Flow", "acronym": "FLOW", "price": 0.47797, "price_currency_exchange": ["USD"], "variance_percent": "+0.91%", "market_cap": "746.71 M", "market_cap_currency_exchange": "USD", "volume": "32 M", "volume_currency_exchange": "USD", "circulating_supply": "1.56 B"},
{"name": "Virtuals Protocol", "acronym": "VIRTUAL", "price": 1.1446, "price_currency_exchange": ["USD"], "variance_percent": "−0.77%", "market_cap": "741.56 M", "market_cap_currency_exchange": "USD", "volume": "178.13 M", "volume_currency_exchange": "USD", "circulating_supply": "647.87 M"},
{"name": "USDD", "acronym": "USDD", "price": 1.0003, "price_currency_exchange": ["USD"], "variance_percent": "−0.06%", "market_cap": "741.31 M", "market_cap_currency_exchange": "USD", "volume": "12.59 M", "volume_currency_exchange": "USD", "circulating_supply": "741.08 M"},
{"name": "Neo", "acronym": "NEO", "price": 10.379, "price_currency_exchange": ["USD"], "variance_percent": "−0.82%", "market_cap": "732.12 M", "market_cap_currency_exchange": "USD", "volume": "41.27 M", "volume_currency_exchange": "USD", "circulating_supply": "70.54 M"},
{"name": "Jito", "acronym": "JTO", "price": 2.4858, "price_currency_exchange": ["USD"], "variance_percent": "−2.36%", "market_cap": "724.09 M", "market_cap_currency_exchange": "USD", "volume": "54.24 M", "volume_currency_exchange": "USD", "circulating_supply": "291.29 M"},
{"name": "Tether Gold", "acronym": "XAUT", "price": 2863.19, "price_currency_exchange": ["USD"], "variance_percent": "−0.73%", "market_cap": "705.85 M", "market_cap_currency_exchange": "USD", "volume": "8.2 M", "volume_currency_exchange": "USD", "circulating_supply": "246.52 K"},
{"name": "dogwifhat", "acronym": "WIF", "price": 0.69758, "price_currency_exchange": ["USD"], "variance_percent": "−3.99%", "market_cap": "696.77 M", "market_cap_currency_exchange": "USD", "volume": "373.81 M", "volume_currency_exchange": "USD", "circulating_supply": "998.84 M"},
{"name": "Official Melania Meme", "acronym": "MELANIA", "price": 1.454, "price_currency_exchange": ["USD"], "variance_percent": "−2.76%", "market_cap": "702.74 M", "market_cap_currency_exchange": "USD", "volume": "74 M", "volume_currency_exchange": "USD", "circulating_supply": "483.31 M"},
{"name": "Aerodrome Finance", "acronym": "AERO", "price": 0.86457, "price_currency_exchange": ["USD"], "variance_percent": "−5.01%", "market_cap": "661.13 M", "market_cap_currency_exchange": "USD", "volume": "42.81 M", "volume_currency_exchange": "USD", "circulating_supply": "764.69 M"},
{"name": "Ronin", "acronym": "RON", "price": 1.0474, "price_currency_exchange": ["USD"], "variance_percent": "+0.72%", "market_cap": "648.75 M", "market_cap_currency_exchange": "USD", "volume": "17.45 M", "volume_currency_exchange": "USD", "circulating_supply": "619.39 M"},
{"name": "Pyth Network", "acronym": "PYTH", "price": 0.17611, "price_currency_exchange": ["USD"], "variance_percent": "−4.24%", "market_cap": "638.4 M", "market_cap_currency_exchange": "USD", "volume": "46.19 M", "volume_currency_exchange": "USD", "circulating_supply": "3.62 B"},
{"name": "FTX Token", "acronym": "FTT", "price": 1.9361, "price_currency_exchange": ["USD"], "variance_percent": "−2.62%", "market_cap": "636.77 M", "market_cap_currency_exchange": "USD", "volume": "25.62 M", "volume_currency_exchange": "USD", "circulating_supply": "328.9 M"},
{"name": "Axie Infinity", "acronym": "AXS", "price": 4.0184, "price_currency_exchange": ["USD"], "variance_percent": "+1.74%", "market_cap": "636.61 M", "market_cap_currency_exchange": "USD", "volume": "34.52 M", "volume_currency_exchange": "USD", "circulating_supply": "158.42 M"}
]